r00android_fake/__init__.py
r00android_fake/network/__init__.py
r00android_fake/network/gps.py
r00android_fake/network/ip_info.py
r00android_fake/prop/__init__.py
r00android_fake/prop/prop_session.py
r00android_fake-0.1.1.dist-info/METADATA
r00android_fake-0.1.1.dist-info/WHEEL
r00android_fake-0.1.1.dist-info/RECORD
