Metadata-Version: 2.4
Name: r00android_fake
Version: 0.1.1
Requires-Python: >=3.10
Requires-Dist: r00arango-connector
Requires-Dist: requests[socks]
